email_scrapper/__init__.py
email_scrapper/email_settings.py
email_scrapper/models.py
email_scrapper/utils.py
email_scrapper/readers/__init__.py
email_scrapper/readers/base_reader.py
email_scrapper/readers/gmail_reader.py
email_scrapper/readers/smtp_reader.py
email_scrapper/stores/__init__.py
email_scrapper/stores/amazon.py
email_scrapper/stores/bestbuy.py
email_scrapper/stores/ebgames.py
email_scrapper/stores/lego.py
email_scrapper/stores/walmart.py
email_scrapper-0.6.0.dist-info/LICENSE.md
email_scrapper-0.6.0.dist-info/METADATA
email_scrapper-0.6.0.dist-info/WHEEL
email_scrapper-0.6.0.dist-info/top_level.txt
email_scrapper-0.6.0.dist-info/RECORD
