Metadata-Version: 2.1
Name: email-scrapper
Version: 0.6.0
Summary: An email parser for store orders.
Home-page: https://github.com/LucasCLuk/email-scrapper
Author: LucasCLuk
License: UNKNOWN
Platform: UNKNOWN
Classifier: Programming Language :: Python :: 3.6
Classifier: License :: OSI Approved :: MIT License
Classifier: Operating System :: OS Independent
Requires-Dist: lxml
Requires-Dist: pdfminer.six
Requires-Dist: chardet
Requires-Dist: beautifulsoup4
